Metadata-Version: 1.1
Name: iphone-checker
Version: 0.0.1.dev11
Summary: Check nearby Apple stores for iPhone X availability
Home-page: https://github.com/WTFox/iphone-checker
Author: Anthony Fox
Author-email: anthonyfox1988@gmail.com
License: MIT
Keywords: iphone
Platform: UNKNOWN
Classifier: Development Status :: 4 - Beta
Classifier: Environment :: Console
Classifier: Intended Audience :: Developers
Classifier: Intended Audience :: Information Technology
Classifier: License :: OSI Approved :: MIT License
Classifier: Operating System :: OS Independent
Classifier: Programming Language :: Python
